{"timestamp": "Wed Mar 30 14:06:27 2022", "loosers": [{"ticker": "CHWY", "name": "Chewy, Inc.", "change": "-14.04%"}, {"ticker": "MVST", "name": "Microvast Holdings, Inc.", "change": "-12.13%"}, {"ticker": "RH", "name": "RH", "change": "-11.16%"}, {"ticker": "CNXC", "name": "Concentrix Corporation", "change": "-9.18%"}, {"ticker": "RCUS", "name": "Arcus Biosciences, Inc.", "change": "-7.09%"}, {"ticker": "BBBY", "name": "Bed Bath & Beyond Inc.", "change": "-7.09%"}, {"ticker": "W", "name": "Wayfair Inc.", "change": "-5.85%"}, {"ticker": "BRPHF", "name": "Galaxy Digital Holdings Ltd.", "change": "-5.87%"}, {"ticker": "MTTR", "name": "Matterport, Inc.", "change": "-6.36%"}, {"ticker": "GRAB", "name": "Grab Holdings Limited", "change": "-6.01%"}, {"ticker": "TPX", "name": "Tempur Sealy International, Inc.", "change": "-4.58%"}, {"ticker": "AMC", "name": "AMC Entertainment Holdings, Inc.", "change": "-6.12%"}, {"ticker": "PSO", "name": "Pearson plc", "change": "-5.54%"}, {"ticker": "DELHY", "name": "Delivery Hero SE", "change": "-5.42%"}, {"ticker": "GME", "name": "GameStop Corp.", "change": "-5.57%"}, {"ticker": "HOOD", "name": "Robinhood Markets, Inc.", "change": "-5.69%"}, {"ticker": "WSM", "name": "Williams-Sonoma, Inc.", "change": "-5.07%"}, {"ticker": "AER", "name": "AerCap Holdings N.V.", "change": "-4.88%"}, {"ticker": "JXHLY", "name": "ENEOS Holdings, Inc.", "change": "-4.84%"}, {"ticker": "MTDR", "name": "Matador Resources Company", "change": "-4.60%"}, {"ticker": "OSTK", "name": "Overstock.com, Inc.", "change": "-4.93%"}, {"ticker": "VCYT", "name": "Veracyte, Inc.", "change": "-4.24%"}, {"ticker": "TSP", "name": "TuSimple Holdings Inc.", "change": "-4.52%"}, {"ticker": "TME", "name": "Tencent Music Entertainment Group", "change": "-4.22%"}, {"ticker": "SKM", "name": "SK Telecom Co.,Ltd", "change": "-4.22%"}]}