{"timestamp": "Fri Jul 15 15:07:02 2022", "loosers": [{"ticker": "TXG", "name": "10x Genomics, Inc.", "change": "-22.12%"}, {"ticker": "PLUG", "name": "Plug Power Inc.", "change": "-14.59%"}, {"ticker": "IIPR", "name": "Innovative Industrial Properties, Inc.", "change": "-13.10%"}, {"ticker": "SPB", "name": "Spectrum Brands Holdings, Inc.", "change": "-11.79%"}, {"ticker": "RUN", "name": "Sunrun Inc.", "change": "-10.89%"}, {"ticker": "DQ", "name": "Daqo New Energy Corp.", "change": "-10.45%"}, {"ticker": "FSLR", "name": "First Solar, Inc.", "change": "-9.26%"}, {"ticker": "BE", "name": "Bloom Energy Corporation", "change": "-9.40%"}, {"ticker": "NOVA", "name": "Sunnova Energy International Inc.", "change": "-8.28%"}, {"ticker": "ABCL", "name": "AbCellera Biologics Inc.", "change": "-8.06%"}, {"ticker": "YMM", "name": "Full Truck Alliance Co. Ltd.", "change": "-8.02%"}, {"ticker": "RLLCF", "name": "Rolls-Royce Holdings plc", "change": "-6.41%"}, {"ticker": "JKS", "name": "JinkoSolar Holding Co., Ltd.", "change": "-5.57%"}, {"ticker": "LKNCY", "name": "Luckin Coffee Inc.", "change": "-5.78%"}, {"ticker": "BABAF", "name": "Alibaba Group Holding Limited", "change": "-5.62%"}, {"ticker": "SPWR", "name": "SunPower Corporation", "change": "-5.04%"}, {"ticker": "FFIE", "name": "Faraday Future Intelligent Electric Inc.", "change": "-4.00%"}, {"ticker": "IQ", "name": "iQIYI, Inc.", "change": "-4.73%"}, {"ticker": "BILI", "name": "Bilibili Inc.", "change": "-4.81%"}, {"ticker": "VWDRY", "name": "Vestas Wind Systems A/S", "change": "-4.71%"}, {"ticker": "COKE", "name": "Coca-Cola Consolidated, Inc.", "change": "-4.43%"}, {"ticker": "CYTK", "name": "Cytokinetics, Incorporated", "change": "-4.47%"}, {"ticker": "FUTU", "name": "Futu Holdings Limited", "change": "-4.59%"}, {"ticker": "BZ", "name": "Kanzhun Limited", "change": "-4.37%"}, {"ticker": "BEKE", "name": "KE Holdings Inc.", "change": "-4.28%"}]}